[
  {
    "id": 1,
   "url": "https://encrypted-tbn0.gstatic.com/images?q=tbn:ANd9GcRYwTXY0wWjJaKO8AVZgN6X9viGzknSTxPjRA&usqp=CAU" ,
    "description": "dsdsd"
  },


  {
    "id": 2,
   "url": "https://encrypted-tbn0.gstatic.com/images?q=tbn:ANd9GcRYwTXY0wWjJaKO8AVZgN6X9viGzknSTxPjRA&usqp=CAU" ,
    "description": "fasdfeadssdfsdegeewtg"
  },


  {
    "id": 3,
   "url": "https://encrypted-tbn0.gstatic.com/images?q=tbn:ANd9GcRYwTXY0wWjJaKO8AVZgN6X9viGzknSTxPjRA&usqp=CAU" ,
    "description": "tgewrtge4wryghewrahyetrjt"
  },


  {
    "id": 4,
   "url": "https://encrypted-tbn0.gstatic.com/images?q=tbn:ANd9GcRYwTXY0wWjJaKO8AVZgN6X9viGzknSTxPjRA&usqp=CAU" ,
    "description": "etgwgawe4rhyg5e4tjy7tk4wrtgt3e4wtewtgewtgeggesrgsgsfgr"
  },


  {
    "id": 5,
   "url": "https://encrypted-tbn0.gstatic.com/images?q=tbn:ANd9GcRYwTXY0wWjJaKO8AVZgN6X9viGzknSTxPjRA&usqp=CAU" ,
    "description": "dsdsd"
  },


  {
    "id": 6,
   "url": "https://encrypted-tbn0.gstatic.com/images?q=tbn:ANd9GcRYwTXY0wWjJaKO8AVZgN6X9viGzknSTxPjRA&usqp=CAU" ,
    "description": "dsdsd"
  },


  {
    "id": 7,
   "url": "https://encrypted-tbn0.gstatic.com/images?q=tbn:ANd9GcRYwTXY0wWjJaKO8AVZgN6X9viGzknSTxPjRA&usqp=CAU" ,
    "description": "dsdsd"
  },


  {
    "id": 8,
   "url": "https://encrypted-tbn0.gstatic.com/images?q=tbn:ANd9GcRYwTXY0wWjJaKO8AVZgN6X9viGzknSTxPjRA&usqp=CAU" ,
    "description": "dsdsd"
  },


  {
    "id": 9,
   "url": "https://encrypted-tbn0.gstatic.com/images?q=tbn:ANd9GcRYwTXY0wWjJaKO8AVZgN6X9viGzknSTxPjRA&usqp=CAU" ,
    "description": "dsdsd"
  },


  {
    "id": 10,
   "url": "https://encrypted-tbn0.gstatic.com/images?q=tbn:ANd9GcRYwTXY0wWjJaKO8AVZgN6X9viGzknSTxPjRA&usqp=CAU" ,
    "description": "dsdsd"
  },


  {
    "id": 11,
   "url": "https://encrypted-tbn0.gstatic.com/images?q=tbn:ANd9GcRYwTXY0wWjJaKO8AVZgN6X9viGzknSTxPjRA&usqp=CAU" ,
    "description": "dsdsd"
  },


  {
    "id": 12,
   "url": "https://encrypted-tbn0.gstatic.com/images?q=tbn:ANd9GcRYwTXY0wWjJaKO8AVZgN6X9viGzknSTxPjRA&usqp=CAU" ,
    "description": "dsdsd"
  },


  {
    "id": 13,
   "url": "https://encrypted-tbn0.gstatic.com/images?q=tbn:ANd9GcRYwTXY0wWjJaKO8AVZgN6X9viGzknSTxPjRA&usqp=CAU" ,
    "description": "dsdsd"
  },


  {
    "id": 14,
   "url": "https://encrypted-tbn0.gstatic.com/images?q=tbn:ANd9GcRYwTXY0wWjJaKO8AVZgN6X9viGzknSTxPjRA&usqp=CAU" ,
    "description": "dsdsd"
  },


  {
    "id": 15,
   "url": "https://encrypted-tbn0.gstatic.com/images?q=tbn:ANd9GcRYwTXY0wWjJaKO8AVZgN6X9viGzknSTxPjRA&usqp=CAU" ,
    "description": "dsdsd"
  },


  {
    "id": 16,
   "url": "https://encrypted-tbn0.gstatic.com/images?q=tbn:ANd9GcRYwTXY0wWjJaKO8AVZgN6X9viGzknSTxPjRA&usqp=CAU" ,
    "description": "dsdsd"
  }




  ]